nell_scb_lib/_binding.cpython-314-darwin.so
nell_scb_lib/__init__.py
nell_scb_lib/_binding.c
nell_scb_lib/.dylibs/libnghttp3.9.5.1.dylib
nell_scb_lib/.dylibs/libcom_err.3.0.dylib
nell_scb_lib/.dylibs/libngtcp2_crypto_ossl.0.dylib
nell_scb_lib/.dylibs/libbrotlicommon.1.2.0.dylib
nell_scb_lib/.dylibs/libbrotlidec.1.2.0.dylib
nell_scb_lib/.dylibs/libpq.5.dylib
nell_scb_lib/.dylibs/libssl.3.dylib
nell_scb_lib/.dylibs/libngtcp2.16.dylib
nell_scb_lib/.dylibs/libssh2.1.dylib
nell_scb_lib/.dylibs/libcrypto.3.dylib
nell_scb_lib/.dylibs/libgssapi_krb5.2.2.dylib
nell_scb_lib/.dylibs/libnghttp2.14.dylib
nell_scb_lib/.dylibs/libkrb5.3.3.dylib
nell_scb_lib/.dylibs/libcurl.4.dylib
nell_scb_lib/.dylibs/libkrb5support.1.1.dylib
nell_scb_lib/.dylibs/libk5crypto.3.1.dylib
nell_scb_lib/.dylibs/librtmp.1.dylib
nell_scb_lib/.dylibs/libzstd.1.5.7.dylib
nell_scb_lib-1.7.0.dist-info/RECORD
nell_scb_lib-1.7.0.dist-info/WHEEL
nell_scb_lib-1.7.0.dist-info/top_level.txt
nell_scb_lib-1.7.0.dist-info/METADATA
nell_scb_lib-1.7.0.dist-info/licenses/LICENSE
