Metadata-Version: 2.4
Name: nell-scb-lib
Version: 1.7.0
Summary: Nellika SCB Payment Integration - Hardened C Module (Commercial License Required)
Home-page: https://nellika.co.th
Author: Danny G.
Author-email: "Danny G." <danny.g@nellika.co.th>
Maintainer: Nellika Consulting Services
Maintainer-email: Nellika Consulting Services <support@nellika.co.th>
License: Proprietary - Commercial License Required
Project-URL: Homepage, https://nellika.co.th
Keywords: scb,promptpay,qr,payment,thailand,banking,nellika
Classifier: Development Status :: 5 - Production/Stable
Classifier: Intended Audience :: Developers
Classifier: License :: Other/Proprietary License
Classifier: Operating System :: POSIX :: Linux
Classifier: Operating System :: MacOS :: MacOS X
Classifier: Programming Language :: C
Classifier: Programming Language :: Python :: 3
Classifier: Programming Language :: Python :: 3.9
Classifier: Programming Language :: Python :: 3.10
Classifier: Programming Language :: Python :: 3.11
Classifier: Programming Language :: Python :: 3.12
Classifier: Programming Language :: Python :: 3.13
Classifier: Programming Language :: Python :: 3.14
Classifier: Topic :: Office/Business :: Financial
Classifier: Topic :: Software Development :: Libraries :: Python Modules
Requires-Python: >=3.9
License-File: LICENSE
Dynamic: author
Dynamic: home-page
Dynamic: license-file
Dynamic: maintainer
Dynamic: requires-python
